hyper_connect_test/LICENSE
hyper_connect_test/README.md
hyper_connect_test/__init__.py
hyper_connect_test/_hyper_connect_test.py
hyper_connect_test/services/__init__.py
hyper_connect_test/services/_cache.py
hyper_connect_test/services/_data.py
hyper_connect_test/types/__init__.py
hyper_connect_test/types/_types.py
hyper_connect_test/utils/__init__.py
hyper_connect_test/utils/_create_hyper_request_params.py
hyper_connect_test/utils/_generate_token.py
hyper_connect_test/utils/_get_host.py
hyper_connect_test/utils/_get_key.py
hyper_connect_test/utils/_get_secret.py
hyper_connect_test/utils/_handle_response.py
hyper_connect_test/utils/_hyper_request.py
hyper_connect_test/utils/_to_data_query.py
hyper_connect_test-0.0.1.dist-info/LICENSE
hyper_connect_test-0.0.1.dist-info/WHEEL
hyper_connect_test-0.0.1.dist-info/METADATA
hyper_connect_test-0.0.1.dist-info/RECORD
